nlqk/__init__.py
nlqk/_version.py
nlqk/defaults.py
nlqk/corpus/__init__.py
nlqk/embedding/__init__.py
nlqk-0.0.2.dist-info/licenses/LICENSE
nlqk-0.0.2.dist-info/METADATA
nlqk-0.0.2.dist-info/WHEEL
nlqk-0.0.2.dist-info/top_level.txt
nlqk-0.0.2.dist-info/RECORD
