Metadata-Version: 2.4
Name: nlqk
Version: 0.0.2
Author: Damir Cavar, Billy Dickson, Koushik Reddy Parukola
Author-email: Damir Cavar <dcavar@acm.org>, Koushik Reddy Parukola <koparu@iu.edu>, "Shane A. Sparks" <sparksashane@gmail.com>, "James B. Graves" <gravjabr@iu.edu>
Project-URL: Homepage, https://nlqk.ai/
Project-URL: Issues, https://github.com/dcavar/nlqk/issues
Classifier: Programming Language :: Python :: 3
Classifier: License :: OSI Approved :: MIT License
Classifier: Operating System :: OS Independent
Requires-Python: >=3.9
License-File: LICENSE
Requires-Dist: numpy>=2.3.1
Dynamic: author
Dynamic: license-file
Dynamic: requires-python
